Workbook

Sheet Visão Geral & Estratégia
A1: PLANO DE APOSENTADORIA: AÇÕES BARSI (BESST) + BITCOIN
A2: Estratégia de Acúmulo de Renda Passiva com Rebalanceamento Dinâmico em Picos de Ciclo
A4: PREMISSAS GERAIS DO PLANO
A5: Aporte Mensal Total | B5: 500 | C5: Valor em R$ investido mensalmente
A6: Prazo do Plano de Acúmulo | B6: 15 | C6: Anos até a aposentadoria
A7: Alocação Mensal - Ações B3 (60%) | B7: =B5*0.6 | C7: Foco em fluxo de dividendos (BESST)
A8: Alocação Mensal - Bitcoin (40%) | B8: =B5*0.4 | C8: Foco em reserva de valor e ganho de capital
A9: Dividend Yield Médio Estimado da Carteira | B9: ='Calendário de Dividendos'!D15 | C9: DY médio ponderado das ações (dinâmico da aba B3)
A10: Crescimento Real Médio das Ações | B10: 0.03 | C10: Valorização média acima da inflação a.a.
A11: Crescimento Real Médio do Bitcoin | B11: 0.15 | C11: Projeção conservadora de valorização real a.a.
A12: Percentual de Reinvestimento de Dividendos | B12: 1 | C12: 100% dos dividendos reinvestidos na fase de acúmulo
A13: Percentual de Realização do BTC nos Picos | B13: 0.25 | C13: Realização parcial em topos de ciclo (a cada 4 anos)
A16: COMPARATIVO DE RESULTADOS APÓS 15 ANOS
A17: Métrica de Desempenho | B17: Estratégia Estática (Buy & Hold) | C17: Estratégia Dinâmica (Rebalanceamento BTC) | D17: Ganho Adicional (R$) | E17: Diferença (%)
A18: Patrimônio Acumulado em Ações | B18: ='Simulação 15 Anos'!C19 | C18: ='Simulação 15 Anos'!G19 | D18: =C18-B18 | E18: =IF(B18>0, (C18-B18)/B18, 0)
A19: Patrimônio Acumulado em Bitcoin | B19: ='Simulação 15 Anos'!D19 | C19: ='Simulação 15 Anos'!H19 | D19: =C19-B19 | E19: =IF(B19>0, (C19-B19)/B19, 0)
A20: Patrimônio Total Acumulado | B20: ='Simulação 15 Anos'!E19 | C20: ='Simulação 15 Anos'!I19 | D20: =C20-B20 | E20: =IF(B20>0, (C20-B20)/B20, 0)
A21: Renda Mensal em Dividendos (Ano 15) | B21: ='Simulação 15 Anos'!F19 | C21: ='Simulação 15 Anos'!J19 | D21: =C21-B21 | E21: =IF(B21>0, (C21-B21)/B21, 0)

Sheet Calendário de Dividendos
A1: CARTEIRA DE AÇÕES RECOMENDADA & CALENDÁRIO MENSAL DE PAGAMENTOS
A2: Seleção de Empresas BESST com Atualização Automática de DY e Margem de Segurança
A4: Ticker | B4: Empresa | C4: Setor (BESST) | D4: DY Atual (%) | E4: Fórmula Google Sheets (IMPORTXML) | F4: Cotação (R$) | G4: Preço Teto Barsi (R$) | H4: Margem de Segurança (%) | I4: Aporte Mensal (R$) | J4: Peso (%) | K4: Jan | L4: Fev | M4: Mar | N4: Abr | O4: Mai | P4: Jun | Q4: Jul | R4: Ago | S4: Set | T4: Out | U4: Nov | V4: Dez
A5: BBAS3 | B5: Banco do Brasil | C5: Bancos | D5: 0.0833 | E5: =IFERROR(VALUE(SUBSTITUTE(SUBSTITUTE(IMPORTXML("https://www.fundamentus.com.br/detalhes.php?papel=BBAS3", "//td[span='Div. Yield']/following-sibling::td/span"), "%", ""), ".", ",")), 0.0833) | F5: 21.49 | G5: =(F5*D5)/0.06 | H5: =(G5-F5)/F5 | I5: 75 | J5: =I5/$I$15 | L5: X | M5: X | P5: X | R5: X | S5: X | U5: X | V5: X
A6: ITSA4 | B6: Itaúsa | C6: Holding / Bancos | D6: 0.0809 | E6: =IFERROR(VALUE(SUBSTITUTE(SUBSTITUTE(IMPORTXML("https://www.fundamentus.com.br/detalhes.php?papel=ITSA4", "//td[span='Div. Yield']/following-sibling::td/span"), "%", ""), ".", ",")), 0.0809) | F6: 13.95 | G6: =(F6*D6)/0.06 | H6: =(G6-F6)/F6 | I6: 60 | J6: =I6/$I$15 | K6: X | L6: X | M6: X | N6: X | O6: X | P6: X | Q6: X | R6: X | S6: X | T6: X | U6: X | V6: X
A7: TAEE3 | B7: Taesa | C7: Energia Elétrica | D7: 0.0748 | E7: =IFERROR(VALUE(SUBSTITUTE(SUBSTITUTE(IMPORTXML("https://www.fundamentus.com.br/detalhes.php?papel=TAEE3", "//td[span='Div. Yield']/following-sibling::td/span"), "%", ""), ".", ",")), 0.0748) | F7: 13.33 | G7: =(F7*D7)/0.06 | H7: =(G7-F7)/F7 | I7: 60 | J7: =I7/$I$15 | K7: X | O7: X | R7: X | U7: X
A8: BBSE3 | B8: BB Seguridade | C8: Seguridade | D8: 0.1196 | E8: =IFERROR(VALUE(SUBSTITUTE(SUBSTITUTE(IMPORTXML("https://www.fundamentus.com.br/detalhes.php?papel=BBSE3", "//td[span='Div. Yield']/following-sibling::td/span"), "%", ""), ".", ",")), 0.1196) | F8: 38.38 | G8: =(F8*D8)/0.06 | H8: =(G8-F8)/F8 | I8: 60 | J8: =I8/$I$15 | L8: X | M8: X | R8: X | S8: X
A9: VIVT3 | B9: Telefonica Vivo | C9: Telecomunicações | D9: 0.072 | E9: =IFERROR(VALUE(SUBSTITUTE(SUBSTITUTE(IMPORTXML("https://www.fundamentus.com.br/detalhes.php?papel=VIVT3", "//td[span='Div. Yield']/following-sibling::td/span"), "%", ""), ".", ",")), 0.0720) | F9: 29.51 | G9: =(F9*D9)/0.06 | H9: =(G9-F9)/F9 | I9: 45 | J9: =I9/$I$15 | N9: X | Q9: X | T9: X | V9: X
A10: CXSE3 | B10: Caixa Seguridade | C10: Seguridade | D10: 0.0674 | E10: =IFERROR(VALUE(SUBSTITUTE(SUBSTITUTE(IMPORTXML("https://www.fundamentus.com.br/detalhes.php?papel=CXSE3", "//td[span='Div. Yield']/following-sibling::td/span"), "%", ""), ".", ",")), 0.0674) | F10: 20.11 | G10: =(F10*D10)/0.06 | H10: =(G10-F10)/F10 | I10: 0 | J10: =I10/$I$15 | K10: X | N10: X | O10: X | R10: X | T10: X | U10: X
A11: ITUB4 | B11: Itaú Unibanco | C11: Bancos | D11: 0.0756 | E11: =IFERROR(VALUE(SUBSTITUTE(SUBSTITUTE(IMPORTXML("https://www.fundamentus.com.br/detalhes.php?papel=ITUB4", "//td[span='Div. Yield']/following-sibling::td/span"), "%", ""), ".", ",")), 0.0756) | F11: 41.71 | G11: =(F11*D11)/0.06 | H11: =(G11-F11)/F11 | I11: 0 | J11: =I11/$I$15 | K11: X | L11: X | M11: X | N11: X | O11: X | P11: X | Q11: X | R11: X | S11: X | T11: X | U11: X | V11: X
A12: CMIG4 | B12: Cemig | C12: Energia Elétrica | D12: 0.0824 | E12: =IFERROR(VALUE(SUBSTITUTE(SUBSTITUTE(IMPORTXML("https://www.fundamentus.com.br/detalhes.php?papel=CMIG4", "//td[span='Div. Yield']/following-sibling::td/span"), "%", ""), ".", ",")), 0.0824) | F12: 10.84 | G12: =(F12*D12)/0.06 | H12: =(G12-F12)/F12 | I12: 0 | J12: =I12/$I$15 | M12: X | N12: X | P12: X | S12: X | V12: X
A13: TIMS3 | B13: TIM Brasil | C13: Telecomunicações | D13: 0.08 | E13: =IFERROR(VALUE(SUBSTITUTE(SUBSTITUTE(IMPORTXML("https://www.fundamentus.com.br/detalhes.php?papel=TIMS3", "//td[span='Div. Yield']/following-sibling::td/span"), "%", ""), ".", ",")), 0.0800) | F13: 18.48 | G13: =(F13*D13)/0.06 | H13: =(G13-F13)/F13 | I13: 0 | J13: =I13/$I$15 | K13: X | N13: X | Q13: X | T13: X
A14: BRSR6 | B14: Banrisul | C14: Bancos | D14: 0.1018 | E14: =IFERROR(VALUE(SUBSTITUTE(SUBSTITUTE(IMPORTXML("https://www.fundamentus.com.br/detalhes.php?papel=BRSR6", "//td[span='Div. Yield']/following-sibling::td/span"), "%", ""), ".", ",")), 0.1018) | F14: 15.31 | G14: =(F14*D14)/0.06 | H14: =(G14-F14)/F14 | I14: 0 | J14: =I14/$I$15 | M14: X | O14: X | P14: X | S14: X | V14: X
A15: MÉDIA / TOTAL CARTEIRA AÇÕES | D15: =SUMPRODUCT(D5:D14, J5:J14) | I15: ='Visão Geral & Estratégia'!B7 | J15: =SUM(J5:J14)
A17: * O 'DY Atual (%)' reflete a taxa de dividendos acumulada dos últimos 12 meses obtida nas plataformas financeiras (StatusInvest / Fundamentus).
A18: * A coluna 'Fórmula Google Sheets' contém a instrução =IMPORTXML(...) que você pode colar na coluna D caso use o Google Sheets para atualização 100% automática a cada abertura.
A19: * 'Preço Teto' representa o preço máximo a pagar para garantir no mínimo 6% a.a. de Dividend Yield.

Sheet Simulação 15 Anos
A1: SIMULAÇÃO DETALHADA DE ACÚMULO E REBALANCEAMENTO DINÂMICO (15 ANOS)
A2: Evolução do Patrimônio e Projeção de Renda Passiva de Dividendos
A4: Ano | B4: Aporte Acum. (R$) | C4: Estat. Ações (R$) | D4: Estat. BTC (R$) | E4: Estat. Total (R$) | F4: Estat. Div/Mês (R$) | G4: Dinam. Ações (R$) | H4: Dinam. BTC (R$) | I4: Dinam. Total (R$) | J4: Dinam. Div/Mês (R$) | K4: Evento Rebalanceamento
A5: 1 | B5: ='Visão Geral & Estratégia'!$B$5*12*1 | C5: =-FV(('Visão Geral & Estratégia'!$B$9+'Visão Geral & Estratégia'!$B$10)/12, 1*12, 'Visão Geral & Estratégia'!$B$7, 0) | D5: =-FV('Visão Geral & Estratégia'!$B$11/12, 1*12, 'Visão Geral & Estratégia'!$B$8, 0) | E5: =C5+D5 | F5: =(C5*'Visão Geral & Estratégia'!$B$9)/12 | G5: =C5 | H5: =D5 | I5: =G5+H5 | J5: =(G5*'Visão Geral & Estratégia'!$B$9)/12 | K5: Acúmulo Normal
A6: 2 | B6: ='Visão Geral & Estratégia'!$B$5*12*2 | C6: =-FV(('Visão Geral & Estratégia'!$B$9+'Visão Geral & Estratégia'!$B$10)/12, 2*12, 'Visão Geral & Estratégia'!$B$7, 0) | D6: =-FV('Visão Geral & Estratégia'!$B$11/12, 2*12, 'Visão Geral & Estratégia'!$B$8, 0) | E6: =C6+D6 | F6: =(C6*'Visão Geral & Estratégia'!$B$9)/12 | G6: =G5*(1+('Visão Geral & Estratégia'!$B$9+'Visão Geral & Estratégia'!$B$10)) + 'Visão Geral & Estratégia'!$B$7*12 | H6: =H5*(1+'Visão Geral & Estratégia'!$B$11) + 'Visão Geral & Estratégia'!$B$8*12 | I6: =G6+H6 | J6: =(G6*'Visão Geral & Estratégia'!$B$9)/12 | K6: Acúmulo Normal
A7: 3 | B7: ='Visão Geral & Estratégia'!$B$5*12*3 | C7: =-FV(('Visão Geral & Estratégia'!$B$9+'Visão Geral & Estratégia'!$B$10)/12, 3*12, 'Visão Geral & Estratégia'!$B$7, 0) | D7: =-FV('Visão Geral & Estratégia'!$B$11/12, 3*12, 'Visão Geral & Estratégia'!$B$8, 0) | E7: =C7+D7 | F7: =(C7*'Visão Geral & Estratégia'!$B$9)/12 | G7: =G6*(1+('Visão Geral & Estratégia'!$B$9+'Visão Geral & Estratégia'!$B$10)) + 'Visão Geral & Estratégia'!$B$7*12 | H7: =H6*(1+'Visão Geral & Estratégia'!$B$11) + 'Visão Geral & Estratégia'!$B$8*12 | I7: =G7+H7 | J7: =(G7*'Visão Geral & Estratégia'!$B$9)/12 | K7: Acúmulo Normal
A8: 4 | B8: ='Visão Geral & Estratégia'!$B$5*12*4 | C8: =-FV(('Visão Geral & Estratégia'!$B$9+'Visão Geral & Estratégia'!$B$10)/12, 4*12, 'Visão Geral & Estratégia'!$B$7, 0) | D8: =-FV('Visão Geral & Estratégia'!$B$11/12, 4*12, 'Visão Geral & Estratégia'!$B$8, 0) | E8: =C8+D8 | F8: =(C8*'Visão Geral & Estratégia'!$B$9)/12 | G8: =(G7*(1+('Visão Geral & Estratégia'!$B$9+'Visão Geral & Estratégia'!$B$10)) + 'Visão Geral & Estratégia'!$B$7*12) + (H7*(1+'Visão Geral & Estratégia'!$B$11) + 'Visão Geral & Estratégia'!$B$8*12)*'Visão Geral & Estratégia'!$B$13 | H8: =(H7*(1+'Visão Geral & Estratégia'!$B$11) + 'Visão Geral & Estratégia'!$B$8*12)*(1-'Visão Geral & Estratégia'!$B$13) | I8: =G8+H8 | J8: =(G8*'Visão Geral & Estratégia'!$B$9)/12 | K8: Topo BTC: Venda 25% BTC -> Ações
A9: 5 | B9: ='Visão Geral & Estratégia'!$B$5*12*5 | C9: =-FV(('Visão Geral & Estratégia'!$B$9+'Visão Geral & Estratégia'!$B$10)/12, 5*12, 'Visão Geral & Estratégia'!$B$7, 0) | D9: =-FV('Visão Geral & Estratégia'!$B$11/12, 5*12, 'Visão Geral & Estratégia'!$B$8, 0) | E9: =C9+D9 | F9: =(C9*'Visão Geral & Estratégia'!$B$9)/12 | G9: =G8*(1+('Visão Geral & Estratégia'!$B$9+'Visão Geral & Estratégia'!$B$10)) + 'Visão Geral & Estratégia'!$B$7*12 | H9: =H8*(1+'Visão Geral & Estratégia'!$B$11) + 'Visão Geral & Estratégia'!$B$8*12 | I9: =G9+H9 | J9: =(G9*'Visão Geral & Estratégia'!$B$9)/12 | K9: Acúmulo Normal
A10: 6 | B10: ='Visão Geral & Estratégia'!$B$5*12*6 | C10: =-FV(('Visão Geral & Estratégia'!$B$9+'Visão Geral & Estratégia'!$B$10)/12, 6*12, 'Visão Geral & Estratégia'!$B$7, 0) | D10: =-FV('Visão Geral & Estratégia'!$B$11/12, 6*12, 'Visão Geral & Estratégia'!$B$8, 0) | E10: =C10+D10 | F10: =(C10*'Visão Geral & Estratégia'!$B$9)/12 | G10: =G9*(1+('Visão Geral & Estratégia'!$B$9+'Visão Geral & Estratégia'!$B$10)) + 'Visão Geral & Estratégia'!$B$7*12 | H10: =H9*(1+'Visão Geral & Estratégia'!$B$11) + 'Visão Geral & Estratégia'!$B$8*12 | I10: =G10+H10 | J10: =(G10*'Visão Geral & Estratégia'!$B$9)/12 | K10: Acúmulo Normal
A11: 7 | B11: ='Visão Geral & Estratégia'!$B$5*12*7 | C11: =-FV(('Visão Geral & Estratégia'!$B$9+'Visão Geral & Estratégia'!$B$10)/12, 7*12, 'Visão Geral & Estratégia'!$B$7, 0) | D11: =-FV('Visão Geral & Estratégia'!$B$11/12, 7*12, 'Visão Geral & Estratégia'!$B$8, 0) | E11: =C11+D11 | F11: =(C11*'Visão Geral & Estratégia'!$B$9)/12 | G11: =G10*(1+('Visão Geral & Estratégia'!$B$9+'Visão Geral & Estratégia'!$B$10)) + 'Visão Geral & Estratégia'!$B$7*12 | H11: =H10*(1+'Visão Geral & Estratégia'!$B$11) + 'Visão Geral & Estratégia'!$B$8*12 | I11: =G11+H11 | J11: =(G11*'Visão Geral & Estratégia'!$B$9)/12 | K11: Acúmulo Normal
A12: 8 | B12: ='Visão Geral & Estratégia'!$B$5*12*8 | C12: =-FV(('Visão Geral & Estratégia'!$B$9+'Visão Geral & Estratégia'!$B$10)/12, 8*12, 'Visão Geral & Estratégia'!$B$7, 0) | D12: =-FV('Visão Geral & Estratégia'!$B$11/12, 8*12, 'Visão Geral & Estratégia'!$B$8, 0) | E12: =C12+D12 | F12: =(C12*'Visão Geral & Estratégia'!$B$9)/12 | G12: =(G11*(1+('Visão Geral & Estratégia'!$B$9+'Visão Geral & Estratégia'!$B$10)) + 'Visão Geral & Estratégia'!$B$7*12) + (H11*(1+'Visão Geral & Estratégia'!$B$11) + 'Visão Geral & Estratégia'!$B$8*12)*'Visão Geral & Estratégia'!$B$13 | H12: =(H11*(1+'Visão Geral & Estratégia'!$B$11) + 'Visão Geral & Estratégia'!$B$8*12)*(1-'Visão Geral & Estratégia'!$B$13) | I12: =G12+H12 | J12: =(G12*'Visão Geral & Estratégia'!$B$9)/12 | K12: Topo BTC: Venda 25% BTC -> Ações
A13: 9 | B13: ='Visão Geral & Estratégia'!$B$5*12*9 | C13: =-FV(('Visão Geral & Estratégia'!$B$9+'Visão Geral & Estratégia'!$B$10)/12, 9*12, 'Visão Geral & Estratégia'!$B$7, 0) | D13: =-FV('Visão Geral & Estratégia'!$B$11/12, 9*12, 'Visão Geral & Estratégia'!$B$8, 0) | E13: =C13+D13 | F13: =(C13*'Visão Geral & Estratégia'!$B$9)/12 | G13: =G12*(1+('Visão Geral & Estratégia'!$B$9+'Visão Geral & Estratégia'!$B$10)) + 'Visão Geral & Estratégia'!$B$7*12 | H13: =H12*(1+'Visão Geral & Estratégia'!$B$11) + 'Visão Geral & Estratégia'!$B$8*12 | I13: =G13+H13 | J13: =(G13*'Visão Geral & Estratégia'!$B$9)/12 | K13: Acúmulo Normal
A14: 10 | B14: ='Visão Geral & Estratégia'!$B$5*12*10 | C14: =-FV(('Visão Geral & Estratégia'!$B$9+'Visão Geral & Estratégia'!$B$10)/12, 10*12, 'Visão Geral & Estratégia'!$B$7, 0) | D14: =-FV('Visão Geral & Estratégia'!$B$11/12, 10*12, 'Visão Geral & Estratégia'!$B$8, 0) | E14: =C14+D14 | F14: =(C14*'Visão Geral & Estratégia'!$B$9)/12 | G14: =G13*(1+('Visão Geral & Estratégia'!$B$9+'Visão Geral & Estratégia'!$B$10)) + 'Visão Geral & Estratégia'!$B$7*12 | H14: =H13*(1+'Visão Geral & Estratégia'!$B$11) + 'Visão Geral & Estratégia'!$B$8*12 | I14: =G14+H14 | J14: =(G14*'Visão Geral & Estratégia'!$B$9)/12 | K14: Acúmulo Normal
A15: 11 | B15: ='Visão Geral & Estratégia'!$B$5*12*11 | C15: =-FV(('Visão Geral & Estratégia'!$B$9+'Visão Geral & Estratégia'!$B$10)/12, 11*12, 'Visão Geral & Estratégia'!$B$7, 0) | D15: =-FV('Visão Geral & Estratégia'!$B$11/12, 11*12, 'Visão Geral & Estratégia'!$B$8, 0) | E15: =C15+D15 | F15: =(C15*'Visão Geral & Estratégia'!$B$9)/12 | G15: =G14*(1+('Visão Geral & Estratégia'!$B$9+'Visão Geral & Estratégia'!$B$10)) + 'Visão Geral & Estratégia'!$B$7*12 | H15: =H14*(1+'Visão Geral & Estratégia'!$B$11) + 'Visão Geral & Estratégia'!$B$8*12 | I15: =G15+H15 | J15: =(G15*'Visão Geral & Estratégia'!$B$9)/12 | K15: Acúmulo Normal
A16: 12 | B16: ='Visão Geral & Estratégia'!$B$5*12*12 | C16: =-FV(('Visão Geral & Estratégia'!$B$9+'Visão Geral & Estratégia'!$B$10)/12, 12*12, 'Visão Geral & Estratégia'!$B$7, 0) | D16: =-FV('Visão Geral & Estratégia'!$B$11/12, 12*12, 'Visão Geral & Estratégia'!$B$8, 0) | E16: =C16+D16 | F16: =(C16*'Visão Geral & Estratégia'!$B$9)/12 | G16: =(G15*(1+('Visão Geral & Estratégia'!$B$9+'Visão Geral & Estratégia'!$B$10)) + 'Visão Geral & Estratégia'!$B$7*12) + (H15*(1+'Visão Geral & Estratégia'!$B$11) + 'Visão Geral & Estratégia'!$B$8*12)*'Visão Geral & Estratégia'!$B$13 | H16: =(H15*(1+'Visão Geral & Estratégia'!$B$11) + 'Visão Geral & Estratégia'!$B$8*12)*(1-'Visão Geral & Estratégia'!$B$13) | I16: =G16+H16 | J16: =(G16*'Visão Geral & Estratégia'!$B$9)/12 | K16: Topo BTC: Venda 25% BTC -> Ações
A17: 13 | B17: ='Visão Geral & Estratégia'!$B$5*12*13 | C17: =-FV(('Visão Geral & Estratégia'!$B$9+'Visão Geral & Estratégia'!$B$10)/12, 13*12, 'Visão Geral & Estratégia'!$B$7, 0) | D17: =-FV('Visão Geral & Estratégia'!$B$11/12, 13*12, 'Visão Geral & Estratégia'!$B$8, 0) | E17: =C17+D17 | F17: =(C17*'Visão Geral & Estratégia'!$B$9)/12 | G17: =G16*(1+('Visão Geral & Estratégia'!$B$9+'Visão Geral & Estratégia'!$B$10)) + 'Visão Geral & Estratégia'!$B$7*12 | H17: =H16*(1+'Visão Geral & Estratégia'!$B$11) + 'Visão Geral & Estratégia'!$B$8*12 | I17: =G17+H17 | J17: =(G17*'Visão Geral & Estratégia'!$B$9)/12 | K17: Acúmulo Normal
A18: 14 | B18: ='Visão Geral & Estratégia'!$B$5*12*14 | C18: =-FV(('Visão Geral & Estratégia'!$B$9+'Visão Geral & Estratégia'!$B$10)/12, 14*12, 'Visão Geral & Estratégia'!$B$7, 0) | D18: =-FV('Visão Geral & Estratégia'!$B$11/12, 14*12, 'Visão Geral & Estratégia'!$B$8, 0) | E18: =C18+D18 | F18: =(C18*'Visão Geral & Estratégia'!$B$9)/12 | G18: =G17*(1+('Visão Geral & Estratégia'!$B$9+'Visão Geral & Estratégia'!$B$10)) + 'Visão Geral & Estratégia'!$B$7*12 | H18: =H17*(1+'Visão Geral & Estratégia'!$B$11) + 'Visão Geral & Estratégia'!$B$8*12 | I18: =G18+H18 | J18: =(G18*'Visão Geral & Estratégia'!$B$9)/12 | K18: Acúmulo Normal
A19: 15 | B19: ='Visão Geral & Estratégia'!$B$5*12*15 | C19: =-FV(('Visão Geral & Estratégia'!$B$9+'Visão Geral & Estratégia'!$B$10)/12, 15*12, 'Visão Geral & Estratégia'!$B$7, 0) | D19: =-FV('Visão Geral & Estratégia'!$B$11/12, 15*12, 'Visão Geral & Estratégia'!$B$8, 0) | E19: =C19+D19 | F19: =(C19*'Visão Geral & Estratégia'!$B$9)/12 | G19: =G18*(1+('Visão Geral & Estratégia'!$B$9+'Visão Geral & Estratégia'!$B$10)) + 'Visão Geral & Estratégia'!$B$7*12 | H19: =H18*(1+'Visão Geral & Estratégia'!$B$11) + 'Visão Geral & Estratégia'!$B$8*12 | I19: =G19+H19 | J19: =(G19*'Visão Geral & Estratégia'!$B$9)/12 | K19: Acúmulo Normal
